chemspace/__init__.py
chemspace-0.1.0.dist-info/METADATA
chemspace-0.1.0.dist-info/WHEEL
chemspace-0.1.0.dist-info/RECORD
