Metadata-Version: 2.1
Name: chemspace
Version: 0.1.0
Summary: An open-source library for exploring chemical and reaction space
License: MIT
Author: Daniel Choi
Author-email: choi@ibm.com
Requires-Python: >=3.11,<4.0
Classifier: License :: OSI Approved :: MIT License
Classifier: Programming Language :: Python :: 3
Classifier: Programming Language :: Python :: 3.11
Classifier: Programming Language :: Python :: 3.12
